dome_api_sdk/__init__.py
dome_api_sdk/base_client.py
dome_api_sdk/client.py
dome_api_sdk/types.py
dome_api_sdk/endpoints/__init__.py
dome_api_sdk/endpoints/activity_endpoints.py
dome_api_sdk/endpoints/crypto_prices_client.py
dome_api_sdk/endpoints/crypto_prices_endpoints.py
dome_api_sdk/endpoints/events_endpoints.py
dome_api_sdk/endpoints/kalshi_client.py
dome_api_sdk/endpoints/kalshi_endpoints.py
dome_api_sdk/endpoints/market_endpoints.py
dome_api_sdk/endpoints/matching_markets_endpoints.py
dome_api_sdk/endpoints/orders_endpoints.py
dome_api_sdk/endpoints/polymarket_client.py
dome_api_sdk/endpoints/polymarket_websocket.py
dome_api_sdk/endpoints/wallet_endpoints.py
dome_api_sdk/router/__init__.py
dome_api_sdk/router/polymarket.py
dome_api_sdk/utils/__init__.py
dome_api_sdk/utils/allowances.py
dome_api_sdk/utils/privy.py
dome_api_sdk-1.0.0.dist-info/METADATA
dome_api_sdk-1.0.0.dist-info/WHEEL
dome_api_sdk-1.0.0.dist-info/licenses/LICENSE
dome_api_sdk-1.0.0.dist-info/RECORD
