Metadata-Version: 2.4
Name: dome-api-sdk
Version: 1.0.0
Summary: The Dome SDK - A comprehensive Python SDK for Dome API
Project-URL: Homepage, https://www.domeapi.io/
Project-URL: Documentation, https://docs.domeapi.io/
Author-email: Kurush Dubash <kurush@domeapi.com>, Kunal Roy <kunal@domeapi.com>
License: MIT License
License-File: LICENSE
Keywords: api,client,dome,prediction markets,python,sdk
Classifier: Development Status :: 3 - Alpha
Classifier: Intended Audience :: Developers
Classifier: License :: OSI Approved :: MIT License
Classifier: Operating System :: OS Independent
Classifier: Programming Language :: Python :: 3
Classifier: Programming Language :: Python :: 3.8
Classifier: Programming Language :: Python :: 3.9
Classifier: Programming Language :: Python :: 3.10
Classifier: Programming Language :: Python :: 3.11
Classifier: Programming Language :: Python :: 3.12
Classifier: Topic :: Software Development :: Libraries :: Python Modules
Classifier: Typing :: Typed
Requires-Python: >=3.9
Requires-Dist: httpx>=0.24.0
Requires-Dist: typing-extensions>=4.5.0; python_version < '3.10'
Requires-Dist: websockets>=12.0
Provides-Extra: dev
Requires-Dist: black>=23.0; extra == 'dev'
Requires-Dist: build>=0.10; extra == 'dev'
Requires-Dist: flake8>=6.0; extra == 'dev'
Requires-Dist: isort>=5.12; extra == 'dev'
Requires-Dist: mypy>=1.0; extra == 'dev'
Requires-Dist: pre-commit>=3.0; extra == 'dev'
Requires-Dist: pytest-asyncio>=0.21.0; extra == 'dev'
Requires-Dist: pytest-cov>=4.0; extra == 'dev'
Requires-Dist: pytest-httpx>=0.21.0; extra == 'dev'
Requires-Dist: pytest>=7.0; extra == 'dev'
Requires-Dist: twine>=4.0; extra == 'dev'
Provides-Extra: docs
Requires-Dist: mkdocs-material>=9.0; extra == 'docs'
Requires-Dist: mkdocs>=1.4; extra == 'docs'
Requires-Dist: mkdocstrings[python]>=0.20; extra == 'docs'
Provides-Extra: test
Requires-Dist: pytest-asyncio>=0.21.0; extra == 'test'
Requires-Dist: pytest-cov>=4.0; extra == 'test'
Requires-Dist: pytest-httpx>=0.21.0; extra == 'test'
Requires-Dist: pytest>=7.0; extra == 'test'
